<?xml version="1.0" encoding="utf-8"?>
<abapGit version="v1.0.0" serializer="LCL_OBJECT_VIEW" serializer_version="v1.0.0">
 <asx:abap xmlns:asx="http://www.sap.com/abapxml" version="1.0">
  <asx:values>
   <DD25V>
    <VIEWNAME>/ZAK/UREPI_MV</VIEWNAME>
    <AS4LOCAL>A</AS4LOCAL>
    <DDLANGUAGE>H</DDLANGUAGE>
    <AGGTYPE>V</AGGTYPE>
    <ROOTTAB>/ZAK/UREPI</ROOTTAB>
    <DDTEXT>Üzleti ajándék, reprezentáció adómentes adatok karbantartása</DDTEXT>
    <VIEWCLASS>C</VIEWCLASS>
    <CUSTOMAUTH>A</CUSTOMAUTH>
    <GLOBALFLAG>X</GLOBALFLAG>
   </DD25V>
   <DD26V_TABLE>
    <DD26V>
     <VIEWNAME>/ZAK/UREPI_MV</VIEWNAME>
     <TABNAME>/ZAK/UREPI</TABNAME>
     <TABPOS>0001</TABPOS>
     <FORTABNAME>/ZAK/UREPI</FORTABNAME>
    </DD26V>
   </DD26V_TABLE>
   <DD27P_TABLE>
    <DD27P>
     <VIEWFIELD>MANDT</VIEWFIELD>
     <TABNAME>/ZAK/UREPI</TABNAME>
     <FIELDNAME>MANDT</FIELDNAME>
     <KEYFLAG>X</KEYFLAG>
     <RDONLY>H</RDONLY>
     <CHECKTABLE>T000</CHECKTABLE>
     <SHLPORIGIN>P</SHLPORIGIN>
    </DD27P>
    <DD27P>
     <VIEWFIELD>BUKRS</VIEWFIELD>
     <TABNAME>/ZAK/UREPI</TABNAME>
     <FIELDNAME>BUKRS</FIELDNAME>
     <KEYFLAG>X</KEYFLAG>
     <CHECKTABLE>T001</CHECKTABLE>
     <SHLPORIGIN>P</SHLPORIGIN>
     <SHLPNAME>C_T001</SHLPNAME>
     <SHLPFIELD>BUKRS</SHLPFIELD>
     <LOGFLAG>X</LOGFLAG>
    </DD27P>
    <DD27P>
     <VIEWFIELD>GJAHR</VIEWFIELD>
     <TABNAME>/ZAK/UREPI</TABNAME>
     <FIELDNAME>GJAHR</FIELDNAME>
     <KEYFLAG>X</KEYFLAG>
     <LOGFLAG>X</LOGFLAG>
    </DD27P>
    <DD27P>
     <VIEWFIELD>WAERS</VIEWFIELD>
     <TABNAME>/ZAK/UREPI</TABNAME>
     <FIELDNAME>WAERS</FIELDNAME>
     <CHECKTABLE>TCURC</CHECKTABLE>
     <SHLPORIGIN>P</SHLPORIGIN>
     <LOGFLAG>X</LOGFLAG>
    </DD27P>
    <DD27P>
     <VIEWFIELD>UZADM</VIEWFIELD>
     <TABNAME>/ZAK/UREPI</TABNAME>
     <FIELDNAME>UZADM</FIELDNAME>
     <REFTABLE>/ZAK/UREPI</REFTABLE>
     <REFFIELD>WAERS</REFFIELD>
     <LOGFLAG>X</LOGFLAG>
    </DD27P>
    <DD27P>
     <VIEWFIELD>READM</VIEWFIELD>
     <TABNAME>/ZAK/UREPI</TABNAME>
     <FIELDNAME>READM</FIELDNAME>
     <REFTABLE>/ZAK/UREPI</REFTABLE>
     <REFFIELD>WAERS</REFFIELD>
     <LOGFLAG>X</LOGFLAG>
    </DD27P>
    <DD27P>
     <VIEWFIELD>AS4USER</VIEWFIELD>
     <TABNAME>/ZAK/UREPI</TABNAME>
     <FIELDNAME>AS4USER</FIELDNAME>
     <RDONLY>R</RDONLY>
    </DD27P>
    <DD27P>
     <VIEWFIELD>AS4DATE</VIEWFIELD>
     <TABNAME>/ZAK/UREPI</TABNAME>
     <FIELDNAME>AS4DATE</FIELDNAME>
     <RDONLY>R</RDONLY>
     <SHLPORIGIN>T</SHLPORIGIN>
    </DD27P>
    <DD27P>
     <VIEWFIELD>AS4TIME</VIEWFIELD>
     <TABNAME>/ZAK/UREPI</TABNAME>
     <FIELDNAME>AS4TIME</FIELDNAME>
     <RDONLY>R</RDONLY>
     <SHLPORIGIN>T</SHLPORIGIN>
    </DD27P>
   </DD27P_TABLE>
   <TABL_EXTRAS>
    <TDDAT>
     <TABNAME>/ZAK/UREPI_MV</TABNAME>
     <CCLASS>/ZAK</CCLASS>
    </TDDAT>
   </TABL_EXTRAS>
   <I18N_LANGS>
    <LANGU>D</LANGU>
   </I18N_LANGS>
   <DD25_TEXTS>
    <item>
     <DDLANGUAGE>D</DDLANGUAGE>
     <DDTEXT>Geschäftsgeschenk, Representations, Steuerfreie Daten</DDTEXT>
    </item>
   </DD25_TEXTS>
  </asx:values>
 </asx:abap>
</abapGit>
